LICENCE
README.rst
setup.py
flask_neon_kit/__init__.py
flask_neon_kit/flask_neon_kit.py
flask_neon_kit/utils.py
flask_neon_kit.egg-info/PKG-INFO
flask_neon_kit.egg-info/SOURCES.txt
flask_neon_kit.egg-info/dependency_links.txt
flask_neon_kit.egg-info/requires.txt
flask_neon_kit.egg-info/top_level.txt