Metadata-Version: 2.1
Name: flask-neon-kit
Version: 0.0.4
Summary: Automatically generates Flask CRUD endpoints from defined Neon Postgres models
Home-page: 
Author: Valentine Sean Chanengeta
Author-email: seanchanengeta@gmail.com
License: MIT
Keywords: neon-oss-starter-kit,flask-neon-kit,flask-crud
Classifier: Development Status :: 3 - Alpha
Classifier: Intended Audience :: Developers
Classifier: Operating System :: Microsoft :: Windows :: Windows 10
Classifier: Operating System :: POSIX :: Linux
Classifier: Operating System :: MacOS :: MacOS X
Classifier: License :: OSI Approved :: MIT License
Classifier: Programming Language :: Python :: 3
License-File: LICENCE
